CHANGES.rst
CONTRIBUTORS.rst
MANIFEST.in
Makefile
README.rst
requirements-4.3.txt
setup.cfg
setup.py
docs/LICENSE.GPL
docs/LICENSE.rst
docs/index.rst
src/imio/__init__.py
src/imio.zamqp.dms.egg-info/PKG-INFO
src/imio.zamqp.dms.egg-info/SOURCES.txt
src/imio.zamqp.dms.egg-info/dependency_links.txt
src/imio.zamqp.dms.egg-info/entry_points.txt
src/imio.zamqp.dms.egg-info/namespace_packages.txt
src/imio.zamqp.dms.egg-info/not-zip-safe
src/imio.zamqp.dms.egg-info/requires.txt
src/imio.zamqp.dms.egg-info/top_level.txt
src/imio/zamqp/__init__.py
src/imio/zamqp/dms/__init__.py
src/imio/zamqp/dms/configure.zcml
src/imio/zamqp/dms/consumer.py
src/imio/zamqp/dms/interfaces.py
src/imio/zamqp/dms/testing.py
src/imio/zamqp/dms/locales/generated.pot
src/imio/zamqp/dms/locales/imio.zamqp.dms.pot
src/imio/zamqp/dms/locales/update.sh
src/imio/zamqp/dms/locales/en/LC_MESSAGES/imio.zamqp.dms.po
src/imio/zamqp/dms/locales/fr/LC_MESSAGES/imio.zamqp.dms.po
src/imio/zamqp/dms/tests/__init__.py
src/imio/zamqp/dms/tests/test_incoming_email.py