Metadata-Version: 2.1
Name: imio.zamqp.dms
Version: 0.22.0
Summary: zamqp consumer for imio.dms.mail
Author: IMIO
Author-email: devs@imio.be
License: GPL version 2
Project-URL: PyPI, https://pypi.python.org/pypi/imio.zamqp.dms
Project-URL: Source, https://github.com/imio/imio.zamqp.dms
Keywords: amqp dms document management system
Classifier: Development Status :: 5 - Production/Stable
Classifier: Environment :: Web Environment
Classifier: Framework :: Plone
Classifier: Framework :: Plone :: 4.3
Classifier: License :: OSI Approved :: GNU General Public License v2 (GPLv2)
Classifier: Programming Language :: Python
Classifier: Programming Language :: Python :: 2.7
Classifier: Operating System :: OS Independent
Requires-Dist: plone.api
Requires-Dist: Products.GenericSetup>=1.8.2
Requires-Dist: setuptools
Requires-Dist: imio.dms.mail
Requires-Dist: imio.zamqp.core
Provides-Extra: test
Requires-Dist: imio.dms.mail[test]; extra == "test"
